filecrawl/__init__.py
filecrawl/colors.py
filecrawl/config_handling.py
filecrawl/crawler.py
filecrawl/filehandling.py
filecrawl-1.0.0.dist-info/LICENSE
filecrawl-1.0.0.dist-info/LICENSE-setup
filecrawl-1.0.0.dist-info/METADATA
filecrawl-1.0.0.dist-info/WHEEL
filecrawl-1.0.0.dist-info/top_level.txt
filecrawl-1.0.0.dist-info/RECORD
