Metadata-Version: 2.1
Name: filecrawl
Version: 1.0.0
Summary: A simple crawler obtaining all available files from the campus management platform Studip and moodle for University Trier
Home-page: https://github.com/Xceron/studipcrawl
Author: Florian Brand
Author-email: github@florianbrand.de
License: MIT
Platform: UNKNOWN
Classifier: License :: OSI Approved :: MIT License
Classifier: Programming Language :: Python
Classifier: Programming Language :: Python :: 3
Classifier: Programming Language :: Python :: 3.4
Classifier: Programming Language :: Python :: 3.5
Classifier: Programming Language :: Python :: 3.6
Classifier: Programming Language :: Python :: 3.7
Classifier: Programming Language :: Python :: Implementation :: CPython
Classifier: Programming Language :: Python :: Implementation :: PyPy
Requires-Python: >=3.4.0
Requires-Dist: colorama
Requires-Dist: astroid (==2.2.3)
Requires-Dist: beautifulsoup4 (==4.7.1)
Requires-Dist: certifi (==2018.11.29)
Requires-Dist: chardet (==3.0.4)
Requires-Dist: entrypoints (==0.3)
Requires-Dist: idna (==2.8)
Requires-Dist: isort (==4.3.10)
Requires-Dist: keyring (==19.0.1)
Requires-Dist: lazy-object-proxy (==1.3.1)
Requires-Dist: mccabe (==0.6.1)
Requires-Dist: pylint (==2.3.1)
Requires-Dist: requests (==2.21.0)
Requires-Dist: six (==1.12.0)
Requires-Dist: soupsieve (==1.8)
Requires-Dist: typed-ast (==1.3.1)
Requires-Dist: urllib3 (==1.24.2)
Requires-Dist: wrapt (==1.11.1)
